FancyBoxes/FancyBoxes.py
FancyBoxes/__init__.py
fancyboxes-1.2.0.dist-info/METADATA
fancyboxes-1.2.0.dist-info/WHEEL
fancyboxes-1.2.0.dist-info/licenses/LICENSE
fancyboxes-1.2.0.dist-info/RECORD
